mkdocs_quiz/__init__.py
mkdocs_quiz/parsing.py
mkdocs_quiz/plugin.py
mkdocs_quiz/translations.py
mkdocs_quiz/cli/__init__.py
mkdocs_quiz/cli/discovery.py
mkdocs_quiz/cli/fetcher.py
mkdocs_quiz/cli/history.py
mkdocs_quiz/cli/main.py
mkdocs_quiz/cli/runner.py
mkdocs_quiz/css/__init__.py
mkdocs_quiz/css/quiz.css
mkdocs_quiz/js/__init__.py
mkdocs_quiz/js/quiz.js
mkdocs_quiz/js/vendor/__init__.py
mkdocs_quiz/js/vendor/js-confetti.browser.js
mkdocs_quiz/locales/de.po
mkdocs_quiz/locales/eo.po
mkdocs_quiz/locales/es.po
mkdocs_quiz/locales/fr.po
mkdocs_quiz/locales/hi.po
mkdocs_quiz/locales/id.po
mkdocs_quiz/locales/ja.po
mkdocs_quiz/locales/ko.po
mkdocs_quiz/locales/mkdocs_quiz.pot
mkdocs_quiz/locales/no.po
mkdocs_quiz/locales/pt-BR.po
mkdocs_quiz/locales/sv.po
mkdocs_quiz/locales/zh.po
mkdocs_quiz/overrides/main.html
mkdocs_quiz/qti/__init__.py
mkdocs_quiz/qti/base.py
mkdocs_quiz/qti/extractor.py
mkdocs_quiz/qti/models.py
mkdocs_quiz/qti/qti12.py
mkdocs_quiz/qti/qti21.py
mkdocs_quiz/qti/utils.py
mkdocs_quiz-1.5.4.dist-info/licenses/LICENSE
mkdocs_quiz-1.5.4.dist-info/METADATA
mkdocs_quiz-1.5.4.dist-info/WHEEL
mkdocs_quiz-1.5.4.dist-info/entry_points.txt
mkdocs_quiz-1.5.4.dist-info/top_level.txt
mkdocs_quiz-1.5.4.dist-info/RECORD
