Metadata-Version: 2.4
Name: mkdocs_quiz
Version: 1.5.4
Summary: A MkDocs plugin to create interactive quizzes in your markdown.
Author-email: Phil Ewels <phil.ewels@seqera.io>, Sebastian Jörz <sjoerz@skyface.de>
License: Apache License 2.0
Project-URL: Homepage, https://ewels.github.io/mkdocs-quiz/
Project-URL: Documentation, https://github.com/ewels/mkdocs-quiz
Project-URL: Repository, https://github.com/ewels/mkdocs-quiz
Project-URL: Issues, https://github.com/ewels/mkdocs-quiz/issues
Keywords: mkdocs,quiz,plugin,markdown,mkdocs-material,multiple-choice,exam,questions-and-answers
Classifier: Development Status :: 4 - Beta
Classifier: Intended Audience :: Developers
Classifier: Intended Audience :: Education
Classifier: License :: OSI Approved :: Apache Software License
Classifier: Programming Language :: Python :: 3
Classifier: Programming Language :: Python :: 3.9
Classifier: Programming Language :: Python :: 3.10
Classifier: Programming Language :: Python :: 3.11
Classifier: Programming Language :: Python :: 3.12
Classifier: Programming Language :: Python :: 3.13
Classifier: Programming Language :: Python :: 3.14
Classifier: Topic :: Documentation
Classifier: Topic :: Software Development :: Documentation
Classifier: Typing :: Typed
Requires-Python: >=3.9
License-File: LICENSE
Requires-Dist: mkdocs>=1.0.0
Requires-Dist: importlib-resources>=5.0; python_version < "3.9"
Requires-Dist: polib>=1.1.0
Requires-Dist: questionary>=2.0.0
Requires-Dist: requests>=2.25.0
Requires-Dist: rich-click>=1.7.0
Provides-Extra: dev
Requires-Dist: pytest>=7.0.0; extra == "dev"
Requires-Dist: pytest-cov>=4.0.0; extra == "dev"
Requires-Dist: pytest-playwright>=0.4.0; extra == "dev"
Requires-Dist: ruff>=0.8.0; extra == "dev"
Requires-Dist: mypy>=1.0.0; extra == "dev"
Requires-Dist: pre-commit>=3.0.0; extra == "dev"
Requires-Dist: babel>=2.9.0; extra == "dev"
Requires-Dist: types-polib>=1.0.0; extra == "dev"
Requires-Dist: types-Markdown; extra == "dev"
Requires-Dist: tomli>=2.0.0; python_version < "3.11" and extra == "dev"
Provides-Extra: docs
Requires-Dist: mkdocs-material; extra == "docs"
Dynamic: license-file
